pytesdaq/__init__.py
pytesdaq/_version.py
pytesdaq/analyzer/__init__.py
pytesdaq/analyzer/analyzer.py
pytesdaq/config/__init__.py
pytesdaq/config/settings.py
pytesdaq/daq/__init__.py
pytesdaq/daq/daq.py
pytesdaq/daq/daqcontrol.py
pytesdaq/daq/nidaqtask.py
pytesdaq/daq/polaris.py
pytesdaq/display/__init__.py
pytesdaq/display/series.py
pytesdaq/instruments/__init__.py
pytesdaq/instruments/communication.py
pytesdaq/instruments/control.py
pytesdaq/instruments/agilent/__init__.py
pytesdaq/instruments/agilent/agilent33500B.py
pytesdaq/instruments/feb/__init__.py
pytesdaq/instruments/feb/feb.py
pytesdaq/instruments/imacrt/__init__.py
pytesdaq/instruments/imacrt/imacrt.py
pytesdaq/instruments/imacrt/macrtmodule.py
pytesdaq/instruments/keithley/__init__.py
pytesdaq/instruments/keithley/keithley2400.py
pytesdaq/instruments/keysight/__init__.py
pytesdaq/instruments/keysight/keysightDSOX1200.py
pytesdaq/instruments/lakeshore/__init__.py
pytesdaq/instruments/lakeshore/lakeshore.py
pytesdaq/instruments/magnicon/__init__.py
pytesdaq/instruments/magnicon/magnicon.py
pytesdaq/instruments/niadc/__init__.py
pytesdaq/instruments/niadc/nidevice.py
pytesdaq/instruments/rigol/__init__.py
pytesdaq/instruments/rigol/rigoldg800.py
pytesdaq/io/__init__.py
pytesdaq/io/filter_hdf5.py
pytesdaq/io/hdf5.py
pytesdaq/io/redis.py
pytesdaq/scope/__init__.py
pytesdaq/scope/readout.py
pytesdaq/scope/scope.py
pytesdaq/sequencer/__init__.py
pytesdaq/sequencer/iv_didv.py
pytesdaq/sequencer/sequencer.py
pytesdaq/sequencer/tc.py
pytesdaq/utils/__init__.py
pytesdaq/utils/arg_utils.py
pytesdaq/utils/connection_utils.py
pytesdaq/utils/remote.py
pytesdaq-0.4.6.dist-info/METADATA
pytesdaq-0.4.6.dist-info/WHEEL
pytesdaq-0.4.6.dist-info/top_level.txt
pytesdaq-0.4.6.dist-info/RECORD
