Metadata-Version: 2.4
Name: pytesdaq
Version: 0.4.6
Summary: DAQ and Intruments control for TES development
Home-page: https://github.com/spice-herald/pytesdaq
Author: Bruno Serfass
Author-email: serfass@berkeley.edu
Requires-Dist: PyQt5
Requires-Dist: matplotlib
Requires-Dist: lakeshore
Requires-Dist: pandas
Requires-Dist: nidaqmx
Requires-Dist: pyvisa
Requires-Dist: paramiko>=3.2.0
Requires-Dist: walrus
Requires-Dist: h5py
Requires-Dist: qetpy>=1.8.0
Requires-Dist: scipy
Requires-Dist: seaborn
Requires-Dist: astropy
Requires-Dist: lmfit
Requires-Dist: tables
Dynamic: author
Dynamic: author-email
Dynamic: description
Dynamic: description-content-type
Dynamic: home-page
Dynamic: requires-dist
Dynamic: summary
